{
    "surahName": "At-Tur",
    "surahNameArabic": "الطور",
    "surahNameArabicLong": "سورة الطور",
    "surahNameTranslation": "The Mount",
    "revelationPlace": "Mecca",
    "totalAyah": 49,
    "surahNo": 52,
    "ayahNo": 39,
    "audio": {
        "1": {
            "reciter": "Mishary Rashid Al Afasy",
            "url": "https://the-quran-project.github.io/Quran-Audio/Data/1/52_39.mp3",
            "originalUrl": "https://everyayah.com/data/Alafasy_128kbps/052039.mp3"
        },
        "2": {
            "reciter": "Abu Bakr Al Shatri",
            "url": "https://the-quran-project.github.io/Quran-Audio/Data/2/52_39.mp3",
            "originalUrl": "https://everyayah.com/data/Abu_Bakr_Ash-Shaatree_128kbps/052039.mp3"
        },
        "3": {
            "reciter": "Nasser Al Qatami",
            "url": "https://the-quran-project.github.io/Quran-Audio/Data/3/52_39.mp3",
            "originalUrl": "https://everyayah.com/data/Nasser_Alqatami_128kbps/052039.mp3"
        },
        "4": {
            "reciter": "Yasser Al Dosari",
            "url": "https://the-quran-project.github.io/Quran-Audio/Data/4/52_39.mp3",
            "originalUrl": "https://everyayah.com/data/Yasser_Ad-Dussary_128kbps/052039.mp3"
        },
        "5": {
            "reciter": "Hani Ar Rifai",
            "url": "https://the-quran-project.github.io/Quran-Audio/Data/5/52_39.mp3",
            "originalUrl": "https://everyayah.com/data/Hani_Rifai_192kbps/052039.mp3"
        }
    },
    "english": "Or does He have daughters ˹as you claim˺, while you ˹prefer to˺ have sons?",
    "arabic1": "أَمْ لَهُ ٱلْبَنَـٰتُ وَلَكُمُ ٱلْبَنُونَ",
    "arabic2": "ام له البنات ولكم البنون",
    "bengali": "তবে কি কন্যাসন্তান তাঁর; আর পুত্রসন্তান তোমাদের?",
    "urdu": "کیا خدا کی تو بیٹیاں اور تمہارے بیٹے"
}