{
    "surahName": "Al-Ahzaab",
    "surahNameArabic": "الأحزاب",
    "surahNameArabicLong": "سورة الأحزاب",
    "surahNameTranslation": "The Clans",
    "revelationPlace": "Madina",
    "totalAyah": 73,
    "surahNo": 33,
    "ayahNo": 40,
    "audio": {
        "1": {
            "reciter": "Mishary Rashid Al Afasy",
            "url": "https://the-quran-project.github.io/Quran-Audio/Data/1/33_40.mp3",
            "originalUrl": "https://everyayah.com/data/Alafasy_128kbps/033040.mp3"
        },
        "2": {
            "reciter": "Abu Bakr Al Shatri",
            "url": "https://the-quran-project.github.io/Quran-Audio/Data/2/33_40.mp3",
            "originalUrl": "https://everyayah.com/data/Abu_Bakr_Ash-Shaatree_128kbps/033040.mp3"
        },
        "3": {
            "reciter": "Nasser Al Qatami",
            "url": "https://the-quran-project.github.io/Quran-Audio/Data/3/33_40.mp3",
            "originalUrl": "https://everyayah.com/data/Nasser_Alqatami_128kbps/033040.mp3"
        },
        "4": {
            "reciter": "Yasser Al Dosari",
            "url": "https://the-quran-project.github.io/Quran-Audio/Data/4/33_40.mp3",
            "originalUrl": "https://everyayah.com/data/Yasser_Ad-Dussary_128kbps/033040.mp3"
        },
        "5": {
            "reciter": "Hani Ar Rifai",
            "url": "https://the-quran-project.github.io/Quran-Audio/Data/5/33_40.mp3",
            "originalUrl": "https://everyayah.com/data/Hani_Rifai_192kbps/033040.mp3"
        }
    },
    "english": "Muḥammad is not the father of any of your men, but is the Messenger of Allah and the seal of the prophets. And Allah has ˹perfect˺ knowledge of all things.",
    "arabic1": "مَّا كَانَ مُحَمَّدٌ أَبَآ أَحَدٍ مِّن رِّجَالِكُمْ وَلَـٰكِن رَّسُولَ ٱللَّهِ وَخَاتَمَ ٱلنَّبِيِّـۧنَ ۗ وَكَانَ ٱللَّهُ بِكُلِّ شَىْءٍ عَلِيمًا",
    "arabic2": "ما كان محمد ابا احد من رجالكم ولكن رسول الله وخاتم النبيين وكان الله بكل شيء عليما",
    "bengali": "মুহাম্মাদ তোমাদের কোন পুরুষের পিতা নয়; তবে আল্লাহর রাসূল ও সর্বশেষ নবী।* আর আল্লাহ সকল বিষয়ে সর্বজ্ঞ। \n* মুহাম্মাদ সাল্লাল্লাহু আলাইহি ওয়াসাল্লাম সর্বশেষ নবী; তাঁর পর আর কোন নবী আসবেন না-এ বিষয়টি আল-কুরআনের এই আয়াত দ্বারা অকাট্যভাবে প্রমাণিত।",
    "urdu": "محمدﷺ تمہارے مردوں میں سے کسی کے والد نہیں ہیں بلکہ خدا کے پیغمبر اور نبیوں (کی نبوت) کی مہر (یعنی اس کو ختم کردینے والے) ہیں اور خدا ہر چیز سے واقف ہے"
}