{
    "surahName": "Al-Mulk",
    "surahNameArabic": "الملك",
    "surahNameArabicLong": "سورة الملك",
    "surahNameTranslation": "The Sovereignty",
    "revelationPlace": "Mecca",
    "totalAyah": 30,
    "surahNo": 67,
    "ayahNo": 13,
    "audio": {
        "1": {
            "reciter": "Mishary Rashid Al Afasy",
            "url": "https://the-quran-project.github.io/Quran-Audio/Data/1/67_13.mp3",
            "originalUrl": "https://everyayah.com/data/Alafasy_128kbps/067013.mp3"
        },
        "2": {
            "reciter": "Abu Bakr Al Shatri",
            "url": "https://the-quran-project.github.io/Quran-Audio/Data/2/67_13.mp3",
            "originalUrl": "https://everyayah.com/data/Abu_Bakr_Ash-Shaatree_128kbps/067013.mp3"
        },
        "3": {
            "reciter": "Nasser Al Qatami",
            "url": "https://the-quran-project.github.io/Quran-Audio/Data/3/67_13.mp3",
            "originalUrl": "https://everyayah.com/data/Nasser_Alqatami_128kbps/067013.mp3"
        },
        "4": {
            "reciter": "Yasser Al Dosari",
            "url": "https://the-quran-project.github.io/Quran-Audio/Data/4/67_13.mp3",
            "originalUrl": "https://everyayah.com/data/Yasser_Ad-Dussary_128kbps/067013.mp3"
        },
        "5": {
            "reciter": "Hani Ar Rifai",
            "url": "https://the-quran-project.github.io/Quran-Audio/Data/5/67_13.mp3",
            "originalUrl": "https://everyayah.com/data/Hani_Rifai_192kbps/067013.mp3"
        }
    },
    "english": "Whether you speak secretly or openly—He surely knows best what is ˹hidden˺ in the heart.",
    "arabic1": "وَأَسِرُّوا۟ قَوْلَكُمْ أَوِ ٱجْهَرُوا۟ بِهِۦٓ ۖ إِنَّهُۥ عَلِيمٌۢ بِذَاتِ ٱلصُّدُورِ",
    "arabic2": "واسروا قولكم او اجهروا به انه عليم بذات الصدور",
    "bengali": "আর তোমরা তোমাদের কথা গোপন কর অথবা তা প্রকাশ কর, নিশ্চয় তিনি অন্তরসমূহে যা আছে সে বিষয়ে সম্যক অবগত।",
    "urdu": "اور تم (لوگ) بات پوشیدہ کہو یا ظاہر۔ وہ دل کے بھیدوں تک سے واقف ہے"
}