{
    "surahName": "Ash-Shu'araa",
    "surahNameArabic": "الشعراء",
    "surahNameArabicLong": "سورة الشعراء",
    "surahNameTranslation": "The Poets",
    "revelationPlace": "Mecca",
    "totalAyah": 227,
    "surahNo": 26,
    "ayahNo": 60,
    "audio": {
        "1": {
            "reciter": "Mishary Rashid Al Afasy",
            "url": "https://the-quran-project.github.io/Quran-Audio/Data/1/26_60.mp3",
            "originalUrl": "https://everyayah.com/data/Alafasy_128kbps/026060.mp3"
        },
        "2": {
            "reciter": "Abu Bakr Al Shatri",
            "url": "https://the-quran-project.github.io/Quran-Audio/Data/2/26_60.mp3",
            "originalUrl": "https://everyayah.com/data/Abu_Bakr_Ash-Shaatree_128kbps/026060.mp3"
        },
        "3": {
            "reciter": "Nasser Al Qatami",
            "url": "https://the-quran-project.github.io/Quran-Audio/Data/3/26_60.mp3",
            "originalUrl": "https://everyayah.com/data/Nasser_Alqatami_128kbps/026060.mp3"
        },
        "4": {
            "reciter": "Yasser Al Dosari",
            "url": "https://the-quran-project.github.io/Quran-Audio/Data/4/26_60.mp3",
            "originalUrl": "https://everyayah.com/data/Yasser_Ad-Dussary_128kbps/026060.mp3"
        },
        "5": {
            "reciter": "Hani Ar Rifai",
            "url": "https://the-quran-project.github.io/Quran-Audio/Data/5/26_60.mp3",
            "originalUrl": "https://everyayah.com/data/Hani_Rifai_192kbps/026060.mp3"
        }
    },
    "english": "And so they pursued them at sunrise.",
    "arabic1": "فَأَتْبَعُوهُم مُّشْرِقِينَ",
    "arabic2": "فاتبعوهم مشرقين",
    "bengali": "তারপর তারা সূর্যোদয়ের প্রাক্কালে তাদের পিছু নিল।",
    "urdu": "تو انہوں نے سورج نکلتے (یعنی صبح کو) ان کا تعاقب کیا"
}