{
    "surahName": "Al-Baqara",
    "surahNameArabic": "البقرة",
    "surahNameArabicLong": "سورة البقرة",
    "surahNameTranslation": "The Cow",
    "revelationPlace": "Madina",
    "totalAyah": 286,
    "surahNo": 2,
    "ayahNo": 221,
    "audio": {
        "1": {
            "reciter": "Mishary Rashid Al Afasy",
            "url": "https://the-quran-project.github.io/Quran-Audio/Data/1/2_221.mp3",
            "originalUrl": "https://everyayah.com/data/Alafasy_128kbps/002221.mp3"
        },
        "2": {
            "reciter": "Abu Bakr Al Shatri",
            "url": "https://the-quran-project.github.io/Quran-Audio/Data/2/2_221.mp3",
            "originalUrl": "https://everyayah.com/data/Abu_Bakr_Ash-Shaatree_128kbps/002221.mp3"
        },
        "3": {
            "reciter": "Nasser Al Qatami",
            "url": "https://the-quran-project.github.io/Quran-Audio/Data/3/2_221.mp3",
            "originalUrl": "https://everyayah.com/data/Nasser_Alqatami_128kbps/002221.mp3"
        },
        "4": {
            "reciter": "Yasser Al Dosari",
            "url": "https://the-quran-project.github.io/Quran-Audio/Data/4/2_221.mp3",
            "originalUrl": "https://everyayah.com/data/Yasser_Ad-Dussary_128kbps/002221.mp3"
        },
        "5": {
            "reciter": "Hani Ar Rifai",
            "url": "https://the-quran-project.github.io/Quran-Audio/Data/5/2_221.mp3",
            "originalUrl": "https://everyayah.com/data/Hani_Rifai_192kbps/002221.mp3"
        }
    },
    "english": "Do not marry polytheistic women until they believe; for a believing slave-woman is better than a free polytheist, even though she may look pleasant to you. And do not marry your women to polytheistic men until they believe, for a believing slave-man is better than a free polytheist, even though he may look pleasant to you. They invite ˹you˺ to the Fire while Allah invites ˹you˺ to Paradise and forgiveness by His grace. He makes His revelations clear to the people so perhaps they will be mindful.",
    "arabic1": "وَلَا تَنكِحُوا۟ ٱلْمُشْرِكَـٰتِ حَتَّىٰ يُؤْمِنَّ ۚ وَلَأَمَةٌ مُّؤْمِنَةٌ خَيْرٌ مِّن مُّشْرِكَةٍ وَلَوْ أَعْجَبَتْكُمْ ۗ وَلَا تُنكِحُوا۟ ٱلْمُشْرِكِينَ حَتَّىٰ يُؤْمِنُوا۟ ۚ وَلَعَبْدٌ مُّؤْمِنٌ خَيْرٌ مِّن مُّشْرِكٍ وَلَوْ أَعْجَبَكُمْ ۗ أُو۟لَـٰٓئِكَ يَدْعُونَ إِلَى ٱلنَّارِ ۖ وَٱللَّهُ يَدْعُوٓا۟ إِلَى ٱلْجَنَّةِ وَٱلْمَغْفِرَةِ بِإِذْنِهِۦ ۖ وَيُبَيِّنُ ءَايَـٰتِهِۦ لِلنَّاسِ لَعَلَّهُمْ يَتَذَكَّرُونَ",
    "arabic2": "ولا تنكحوا المشركات حتى يؤمن ولامة مؤمنة خير من مشركة ولو اعجبتكم ولا تنكحوا المشركين حتى يؤمنوا ولعبد مؤمن خير من مشرك ولو اعجبكم اولئك يدعون الى النار والله يدعو الى الجنة والمغفرة باذنه ويبين اياته للناس لعلهم يتذكرون",
    "bengali": "আর তোমরা মুশরিক নারীদের বিয়ে করো না, যতক্ষণ না তারা ঈমান আনে এবং মুমিন দাসী মুশরিক নারীর চেয়ে নিশ্চয় উত্তম, যদিও সে তোমাদেরকে মুগ্ধ করে। আর মুশরিক পুরুষদের সাথে বিয়ে দিয়ো না, যতক্ষণ না তারা ঈমান আনে। আর একজন মুমিন দাস একজন মুশরিক পুরুষের চেয়ে উত্তম, যদিও সে তোমাদেরকে মুগ্ধ করে। তারা তোমাদেরকে আগুনের দিকে আহবান করে, আর আল্লাহ তাঁর অনুমতিতে তোমাদেরকে জান্নাত ও ক্ষমার দিকে আহবান করেন এবং মানুষের জন্য তাঁর আয়াতসমূহ স্পষ্টরূপে বর্ণনা করেন, যাতে তারা উপদেশ গ্রহণ করতে পারে।",
    "urdu": "اور (مومنو) مشرک عورتوں سے جب تک کہ ایمان نہ لائیں نکاح نہ کرنا۔ کیونکہ مشرک عورت خواہ تم کو کیسی ہی بھلی لگے اس سے مومن لونڈی بہتر ہے۔ اور (اسی طرح) مشرک مرد جب تک ایمان نہ لائیں مومن عورتوں کو ان کو زوجیت میں نہ دینا کیونکہ مشرک (مرد) سے خواہ وہ تم کو کیسا ہی بھلا لگے مومن غلام بہتر ہے۔ یہ (مشرک لوگوں کو) دوزخ کی طرف بلاتے ہیں۔ اور خدا اپنی مہربانی سے بہشت اور بخشش کی طرف بلاتا ہے۔ اور اپنے حکم لوگوں سے کھول کھول کر بیان کرتا ہے تاکہ نصیحت حاصل کریں"
}