{
    "surahName": "Al-Muminoon",
    "surahNameArabic": "المؤمنون",
    "surahNameArabicLong": "سورة المؤمنون",
    "surahNameTranslation": "The Believers",
    "revelationPlace": "Mecca",
    "totalAyah": 118,
    "surahNo": 23,
    "ayahNo": 76,
    "audio": {
        "1": {
            "reciter": "Mishary Rashid Al Afasy",
            "url": "https://the-quran-project.github.io/Quran-Audio/Data/1/23_76.mp3",
            "originalUrl": "https://everyayah.com/data/Alafasy_128kbps/023076.mp3"
        },
        "2": {
            "reciter": "Abu Bakr Al Shatri",
            "url": "https://the-quran-project.github.io/Quran-Audio/Data/2/23_76.mp3",
            "originalUrl": "https://everyayah.com/data/Abu_Bakr_Ash-Shaatree_128kbps/023076.mp3"
        },
        "3": {
            "reciter": "Nasser Al Qatami",
            "url": "https://the-quran-project.github.io/Quran-Audio/Data/3/23_76.mp3",
            "originalUrl": "https://everyayah.com/data/Nasser_Alqatami_128kbps/023076.mp3"
        },
        "4": {
            "reciter": "Yasser Al Dosari",
            "url": "https://the-quran-project.github.io/Quran-Audio/Data/4/23_76.mp3",
            "originalUrl": "https://everyayah.com/data/Yasser_Ad-Dussary_128kbps/023076.mp3"
        },
        "5": {
            "reciter": "Hani Ar Rifai",
            "url": "https://the-quran-project.github.io/Quran-Audio/Data/5/23_76.mp3",
            "originalUrl": "https://everyayah.com/data/Hani_Rifai_192kbps/023076.mp3"
        }
    },
    "english": "And We have already seized them with torment, but they never humbled themselves to their Lord, nor did they ˹submissively˺ appeal ˹to Him˺.",
    "arabic1": "وَلَقَدْ أَخَذْنَـٰهُم بِٱلْعَذَابِ فَمَا ٱسْتَكَانُوا۟ لِرَبِّهِمْ وَمَا يَتَضَرَّعُونَ",
    "arabic2": "ولقد اخذناهم بالعذاب فما استكانوا لربهم وما يتضرعون",
    "bengali": "আর অবশ্যই আমি তাদেরকে আযাব দ্বারা পাকড়াও করলাম, তবুও তারা তাদের রবের কাছে নত হয়নি এবং বিনীত প্রার্থনাও করে না।",
    "urdu": "اور ہم نے ان کو عذاب میں پکڑا تو بھی انہوں نے خدا کے آگے عاجزی نہ کی اور وہ عاجزی کرتے ہی نہیں"
}