{
    "surahName": "Yaseen",
    "surahNameArabic": "يس",
    "surahNameArabicLong": "سورة يس",
    "surahNameTranslation": "Yaseen",
    "revelationPlace": "Mecca",
    "totalAyah": 83,
    "surahNo": 36,
    "ayahNo": 8,
    "audio": {
        "1": {
            "reciter": "Mishary Rashid Al Afasy",
            "url": "https://the-quran-project.github.io/Quran-Audio/Data/1/36_8.mp3",
            "originalUrl": "https://everyayah.com/data/Alafasy_128kbps/036008.mp3"
        },
        "2": {
            "reciter": "Abu Bakr Al Shatri",
            "url": "https://the-quran-project.github.io/Quran-Audio/Data/2/36_8.mp3",
            "originalUrl": "https://everyayah.com/data/Abu_Bakr_Ash-Shaatree_128kbps/036008.mp3"
        },
        "3": {
            "reciter": "Nasser Al Qatami",
            "url": "https://the-quran-project.github.io/Quran-Audio/Data/3/36_8.mp3",
            "originalUrl": "https://everyayah.com/data/Nasser_Alqatami_128kbps/036008.mp3"
        },
        "4": {
            "reciter": "Yasser Al Dosari",
            "url": "https://the-quran-project.github.io/Quran-Audio/Data/4/36_8.mp3",
            "originalUrl": "https://everyayah.com/data/Yasser_Ad-Dussary_128kbps/036008.mp3"
        },
        "5": {
            "reciter": "Hani Ar Rifai",
            "url": "https://the-quran-project.github.io/Quran-Audio/Data/5/36_8.mp3",
            "originalUrl": "https://everyayah.com/data/Hani_Rifai_192kbps/036008.mp3"
        }
    },
    "english": "˹It is as if˺ We have put shackles around their necks up to their chins, so their heads are forced up",
    "arabic1": "إِنَّا جَعَلْنَا فِىٓ أَعْنَـٰقِهِمْ أَغْلَـٰلًا فَهِىَ إِلَى ٱلْأَذْقَانِ فَهُم مُّقْمَحُونَ",
    "arabic2": "انا جعلنا في اعناقهم اغلالا فهي الى الاذقان فهم مقمحون",
    "bengali": "নিশ্চয় আমি তাদের গলায় বেড়ি পরিয়ে দিয়েছি এবং তা চিবুক পর্যন্ত। ফলে তারা ঊর্ধ্বমুখী হয়ে আছে।",
    "urdu": "ہم نے ان کی گردنوں میں طوق ڈال رکھے ہیں اور وہ ٹھوڑیوں تک (پھنسے ہوئے ہیں) تو ان کے سر اُلل رہے ہیں"
}