{
    "surahName": "Ibrahim",
    "surahNameArabic": "ابراهيم",
    "surahNameArabicLong": "سورة ابراهيم",
    "surahNameTranslation": "Abraham",
    "revelationPlace": "Mecca",
    "totalAyah": 52,
    "surahNo": 14,
    "ayahNo": 2,
    "audio": {
        "1": {
            "reciter": "Mishary Rashid Al Afasy",
            "url": "https://the-quran-project.github.io/Quran-Audio/Data/1/14_2.mp3",
            "originalUrl": "https://everyayah.com/data/Alafasy_128kbps/014002.mp3"
        },
        "2": {
            "reciter": "Abu Bakr Al Shatri",
            "url": "https://the-quran-project.github.io/Quran-Audio/Data/2/14_2.mp3",
            "originalUrl": "https://everyayah.com/data/Abu_Bakr_Ash-Shaatree_128kbps/014002.mp3"
        },
        "3": {
            "reciter": "Nasser Al Qatami",
            "url": "https://the-quran-project.github.io/Quran-Audio/Data/3/14_2.mp3",
            "originalUrl": "https://everyayah.com/data/Nasser_Alqatami_128kbps/014002.mp3"
        },
        "4": {
            "reciter": "Yasser Al Dosari",
            "url": "https://the-quran-project.github.io/Quran-Audio/Data/4/14_2.mp3",
            "originalUrl": "https://everyayah.com/data/Yasser_Ad-Dussary_128kbps/014002.mp3"
        },
        "5": {
            "reciter": "Hani Ar Rifai",
            "url": "https://the-quran-project.github.io/Quran-Audio/Data/5/14_2.mp3",
            "originalUrl": "https://everyayah.com/data/Hani_Rifai_192kbps/014002.mp3"
        }
    },
    "english": "Allah, to Whom belongs whatever is in the heavens and whatever is on the earth. And woe to the disbelievers because of a severe torment!",
    "arabic1": "ٱللَّهِ ٱلَّذِى لَهُۥ مَا فِى ٱلسَّمَـٰوَٰتِ وَمَا فِى ٱلْأَرْضِ ۗ وَوَيْلٌ لِّلْكَـٰفِرِينَ مِنْ عَذَابٍ شَدِيدٍ",
    "arabic2": "الله الذي له ما في السماوات وما في الارض وويل للكافرين من عذاب شديد",
    "bengali": "আল্লাহর (পথ), আসমানসমূহ ও যমীনের সব কিছুই যার মালিকানায় এবং কাফিরদের জন্য রয়েছে কঠিন আযাবের দুর্ভোগ।",
    "urdu": "وہ خدا کہ جو کچھ آسمانوں اور زمین میں ہے سب اسی کا ہے۔ اور کافروں کے لیے عذاب سخت (کی وجہ) سے خرابی ہے"
}